MANIFEST.in
README.md
setup.py
ajaximage/__init__.py
ajaximage/apps.py
ajaximage/fields.py
ajaximage/forms.py
ajaximage/image.py
ajaximage/urls.py
ajaximage/utils.py
ajaximage/views.py
ajaximage/widgets.py
ajaximage/locale/ru/LC_MESSAGES/django.mo
ajaximage/locale/ru/LC_MESSAGES/django.po
ajaximage/static/ajaximage/css/bootstrap-progress.min.css
ajaximage/static/ajaximage/css/styles.css
ajaximage/static/ajaximage/js/ajaximage.js
django2_ajaximage.egg-info/PKG-INFO
django2_ajaximage.egg-info/SOURCES.txt
django2_ajaximage.egg-info/dependency_links.txt
django2_ajaximage.egg-info/not-zip-safe
django2_ajaximage.egg-info/requires.txt
django2_ajaximage.egg-info/top_level.txt