Metadata-Version: 2.1
Name: django2-ajaximage
Version: 0.9.0
Summary: Upload images via ajax. Images are optionally resized.
Home-page: https://github.com/bradleyg/django2-ajaximage
Author: Bradley Griffiths(Modified by Daimon)
Author-email: bradley.griffiths@gmail.com
License: UNKNOWN
Platform: UNKNOWN
Classifier: Development Status :: 4 - Beta
Classifier: Environment :: Web Environment
Classifier: Framework :: Django
Classifier: Intended Audience :: Developers
Classifier: License :: OSI Approved :: MIT License
Classifier: Operating System :: OS Independent
Classifier: Programming Language :: Python :: 3.4
